README.md
setup.py
verslilietuva_driver/__init__.py
verslilietuva_driver/api.py
verslilietuva_driver.egg-info/PKG-INFO
verslilietuva_driver.egg-info/SOURCES.txt
verslilietuva_driver.egg-info/dependency_links.txt
verslilietuva_driver.egg-info/not-zip-safe
verslilietuva_driver.egg-info/requires.txt
verslilietuva_driver.egg-info/top_level.txt