Metadata-Version: 2.1
Name: verslilietuva-driver
Version: 0.0.1
Summary: Versli Lietuva EDB controller.
Home-page: https://github.com/drivernet/verslilietuva_driver
Author: Mindey
Author-email: mindey@qq.com
License: ASK FOR PERMISSIONS
Platform: UNKNOWN
Provides-Extra: test
